<?xml version="1.0" encoding="UTF-8"?>
<!DOCTYPE mapper PUBLIC "-//mybatis.org//DTD Mapper 3.0//EN" "http://mybatis.org/dtd/mybatis-3-mapper.dtd">
<mapper namespace="org.ecommerceplatform.dao.UserDOMapper">
  <resultMap id="BaseResultMap" type="org.ecommerceplatform.dataobject.UserDO">
    <!--
      WARNING - @mbg.generated
      This element is automatically generated by MyBatis Generator, do not modify.
      This element was generated on Mon Sep 12 20:51:34 CST 2022.
    -->
    <id column="id" jdbcType="INTEGER" property="id" />
    <result column="name" jdbcType="VARCHAR" property="name" />
    <result column="gender" jdbcType="TINYINT" property="gender" />
    <result column="telephone" jdbcType="VARCHAR" property="telephone" />
  </resultMap>
  <sql id="Base_Column_List">
    <!--
      WARNING - @mbg.generated
      This element is automatically generated by MyBatis Generator, do not modify.
      This element was generated on Mon Sep 12 20:51:34 CST 2022.
    -->
    id, name, gender, telephone
  </sql>
  <select id="selectByTelephone" resultMap="BaseResultMap">
    select
    <include refid="Base_Column_List" />
    from user_info
    where telephone = #{telephone,jdbcType=VARCHAR}
  </select>
  <select id="selectByPrimaryKey" parameterType="java.lang.Integer" resultMap="BaseResultMap">
    <!--
      WARNING - @mbg.generated
      This element is automatically generated by MyBatis Generator, do not modify.
      This element was generated on Mon Sep 12 20:51:34 CST 2022.
    -->
    select 
    <include refid="Base_Column_List" />
    from user_info
    where id = #{id,jdbcType=INTEGER}
  </select>
  <delete id="deleteByPrimaryKey" parameterType="java.lang.Integer">
    <!--
      WARNING - @mbg.generated
      This element is automatically generated by MyBatis Generator, do not modify.
      This element was generated on Mon Sep 12 20:51:34 CST 2022.
    -->
    delete from user_info
    where id = #{id,jdbcType=INTEGER}
  </delete>
  <insert id="insert" parameterType="org.ecommerceplatform.dataobject.UserDO" keyProperty="id" useGeneratedKeys="true">
    <!--
      WARNING - @mbg.generated
      This element is automatically generated by MyBatis Generator, do not modify.
      This element was generated on Mon Sep 12 20:51:34 CST 2022.
    -->
    insert into user_info (id, name, gender, 
      telephone)
    values (#{id,jdbcType=INTEGER}, #{name,jdbcType=VARCHAR}, #{gender,jdbcType=TINYINT}, 
      #{telephone,jdbcType=VARCHAR})
  </insert>
  <insert id="insertSelective" parameterType="org.ecommerceplatform.dataobject.UserDO" keyProperty="id" useGeneratedKeys="true">
    <!--
      WARNING - @mbg.generated
      This element is automatically generated by MyBatis Generator, do not modify.
      This element was generated on Mon Sep 12 20:51:34 CST 2022.
    -->
    insert into user_info
    <trim prefix="(" suffix=")" suffixOverrides=",">
      <if test="id != null">
        id,
      </if>
      <if test="name != null">
        name,
      </if>
      <if test="gender != null">
        gender,
      </if>
      <if test="telephone != null">
        telephone,
      </if>
    </trim>
    <trim prefix="values (" suffix=")" suffixOverrides=",">
      <if test="id != null">
        #{id,jdbcType=INTEGER},
      </if>
      <if test="name != null">
        #{name,jdbcType=VARCHAR},
      </if>
      <if test="gender != null">
        #{gender,jdbcType=TINYINT},
      </if>
      <if test="telephone != null">
        #{telephone,jdbcType=VARCHAR},
      </if>
    </trim>
  </insert>
  <update id="updateByPrimaryKeySelective" parameterType="org.ecommerceplatform.dataobject.UserDO">
    <!--
      WARNING - @mbg.generated
      This element is automatically generated by MyBatis Generator, do not modify.
      This element was generated on Mon Sep 12 20:51:34 CST 2022.
    -->
    update user_info
    <set>
      <if test="name != null">
        name = #{name,jdbcType=VARCHAR},
      </if>
      <if test="gender != null">
        gender = #{gender,jdbcType=TINYINT},
      </if>
      <if test="telephone != null">
        telephone = #{telephone,jdbcType=VARCHAR},
      </if>
    </set>
    where id = #{id,jdbcType=INTEGER}
  </update>
  <update id="updateByPrimaryKey" parameterType="org.ecommerceplatform.dataobject.UserDO">
    <!--
      WARNING - @mbg.generated
      This element is automatically generated by MyBatis Generator, do not modify.
      This element was generated on Mon Sep 12 20:51:34 CST 2022.
    -->
    update user_info
    set name = #{name,jdbcType=VARCHAR},
      gender = #{gender,jdbcType=TINYINT},
      telephone = #{telephone,jdbcType=VARCHAR}
    where id = #{id,jdbcType=INTEGER}
  </update>
</mapper>